notsouid/__init__.py
notsouid/factories.py
notsouid/wrapper.py
notsouid-0.0.3.dist-info/DESCRIPTION.rst
notsouid-0.0.3.dist-info/METADATA
notsouid-0.0.3.dist-info/RECORD
notsouid-0.0.3.dist-info/WHEEL
notsouid-0.0.3.dist-info/metadata.json
notsouid-0.0.3.dist-info/top_level.txt
