Metadata-Version: 2.0
Name: notsouid
Version: 0.0.3
Summary: not so unique ids
Home-page: https://github.com/nicwest/notsouid
Author: Nic West
Author-email: oss@nicwest.com
License: UNKNOWN
Platform: UNKNOWN
Classifier: Development Status :: 5 - Production/Stable
Classifier: Programming Language :: Python :: 3
Classifier: Programming Language :: Python :: 2.7
Classifier: Intended Audience :: Developers
Classifier: Natural Language :: English
Requires-Dist: mock (>=2.0.0)
